bmctool/__init__.py
bmctool/bmc_solver.py
bmctool/bmc_tool.py
bmctool/params.py
bmctool/set_params.py
bmctool/simulate.py
bmctool/library/readme.md
bmctool/library/maintenance/valid_params.yaml
bmctool/library/seq-library/WASABI.seq
bmctool/library/sim-library/config_wasabi.yaml
bmctool/utils/__init__.py
bmctool/utils/eval.py
bmctool/utils/pulses/__init__.py
bmctool/utils/pulses/calc_power_equivalents.py
bmctool/utils/pulses/calculate_phase.py
bmctool/utils/pulses/create_arbitrary_pulse_with_phase.py
bmctool/utils/pulses/make_hanning.py
bmctool/utils/pulses/make_hsexp.py
bmctool/utils/pulses/make_hypsec_half_passage.py
bmctool/utils/seq/__init__.py
bmctool/utils/seq/auxiliary.py
bmctool/utils/seq/write.py
BMCTool-0.6.1.dist-info/LICENSE
BMCTool-0.6.1.dist-info/METADATA
BMCTool-0.6.1.dist-info/WHEEL
BMCTool-0.6.1.dist-info/top_level.txt
BMCTool-0.6.1.dist-info/RECORD
