Metadata-Version: 2.1
Name: BMCTool
Version: 0.6.1
Summary: A python tool to perform Bloch-McConnell (BMC) simulations.
Home-page: https://github.com/schuenke/BMCTool
Author: Patrick Schuenke
Author-email: patrick.schuenke@ptb.de
Keywords: MRI,Bloch,CEST,simulations
Classifier: Programming Language :: Python :: 3
Classifier: Natural Language :: English
Classifier: License :: OSI Approved :: MIT License
Classifier: Operating System :: OS Independent
Requires-Python: >=3.6
License-File: LICENSE
Requires-Dist: numpy (<1.24)
Requires-Dist: matplotlib
Requires-Dist: tqdm
Requires-Dist: PyYAML
Requires-Dist: pypulseq
